covml/__init__.py
covml/data/corona.csv
covml-0.2.dist-info/METADATA
covml-0.2.dist-info/WHEEL
covml-0.2.dist-info/top_level.txt
covml-0.2.dist-info/RECORD
