Metadata-Version: 2.1
Name: covml
Version: 0.2
Summary: Corona ML predictor
Home-page: UNKNOWN
Author: Shaurya Pratap Singh
Author-email: shaurya.p.singh21@gmail.com
License: MIT
Platform: UNKNOWN
